[
  {
    "attempt": 3,
    "targetSwaName": "fca-frontend",
    "targetDefaultHost": "delightful-mushroom-0de67860f.7.azurestaticapps.net",
    "targetGitSha": "c21c4544ced7658f74ca9c026c6c7f2b324679b4",
    "host": "futurecontractorsofamerica.com",
    "deploymentGitSha": "c21c4544ced7658f74ca9c026c6c7f2b324679b4",
    "runtimeGitSha": "c21c4544ced7658f74ca9c026c6c7f2b324679b4",
    "commitWitnessRoute": "/commit-witness-c21c4544ced7658f74ca9c026c6c7f2b324679b4.txt",
    "expectedHosts": [
      "futurecontractorsofamerica.com",
      "www.futurecontractorsofamerica.com",
      "delightful-mushroom-0de67860f.7.azurestaticapps.net"
    ],
    "routeChecks": [
      {
        "route": "/deployment-status.json",
        "status": 200,
        "ok": true
      },
      {
        "route": "/domain-continuity.json",
        "status": 200,
        "ok": true
      },
      {
        "route": "/runtime-fingerprint.txt",
        "status": 200,
        "ok": true
      },
      {
        "route": "/live-shell-verification.html",
        "status": 200,
        "ok": true
      },
      {
        "route": "/host-binding-audit.html",
        "status": 200,
        "ok": true
      },
      {
        "route": "/api-continuity-audit.html",
        "status": 200,
        "ok": true
      },
      {
        "route": "/warranty",
        "status": 200,
        "ok": true
      },
      {
        "route": "/referrals",
        "status": 200,
        "ok": true
      },
      {
        "route": "/commit-witness-c21c4544ced7658f74ca9c026c6c7f2b324679b4.txt",
        "status": 200,
        "ok": true
      }
    ],
    "failures": []
  },
  {
    "attempt": 3,
    "targetSwaName": "fca-frontend",
    "targetDefaultHost": "delightful-mushroom-0de67860f.7.azurestaticapps.net",
    "targetGitSha": "c21c4544ced7658f74ca9c026c6c7f2b324679b4",
    "host": "www.futurecontractorsofamerica.com",
    "deploymentGitSha": "c21c4544ced7658f74ca9c026c6c7f2b324679b4",
    "runtimeGitSha": "c21c4544ced7658f74ca9c026c6c7f2b324679b4",
    "commitWitnessRoute": "/commit-witness-c21c4544ced7658f74ca9c026c6c7f2b324679b4.txt",
    "expectedHosts": [
      "futurecontractorsofamerica.com",
      "www.futurecontractorsofamerica.com",
      "delightful-mushroom-0de67860f.7.azurestaticapps.net"
    ],
    "routeChecks": [
      {
        "route": "/deployment-status.json",
        "status": 200,
        "ok": true
      },
      {
        "route": "/domain-continuity.json",
        "status": 200,
        "ok": true
      },
      {
        "route": "/runtime-fingerprint.txt",
        "status": 200,
        "ok": true
      },
      {
        "route": "/live-shell-verification.html",
        "status": 200,
        "ok": true
      },
      {
        "route": "/host-binding-audit.html",
        "status": 200,
        "ok": true
      },
      {
        "route": "/api-continuity-audit.html",
        "status": 200,
        "ok": true
      },
      {
        "route": "/warranty",
        "status": 200,
        "ok": true
      },
      {
        "route": "/referrals",
        "status": 200,
        "ok": true
      },
      {
        "route": "/commit-witness-c21c4544ced7658f74ca9c026c6c7f2b324679b4.txt",
        "status": 200,
        "ok": true
      }
    ],
    "failures": []
  },
  {
    "attempt": 3,
    "targetSwaName": "fca-frontend",
    "targetDefaultHost": "delightful-mushroom-0de67860f.7.azurestaticapps.net",
    "targetGitSha": "c21c4544ced7658f74ca9c026c6c7f2b324679b4",
    "host": "delightful-mushroom-0de67860f.7.azurestaticapps.net",
    "deploymentGitSha": "c21c4544ced7658f74ca9c026c6c7f2b324679b4",
    "runtimeGitSha": "c21c4544ced7658f74ca9c026c6c7f2b324679b4",
    "commitWitnessRoute": "/commit-witness-c21c4544ced7658f74ca9c026c6c7f2b324679b4.txt",
    "expectedHosts": [
      "futurecontractorsofamerica.com",
      "www.futurecontractorsofamerica.com",
      "delightful-mushroom-0de67860f.7.azurestaticapps.net"
    ],
    "routeChecks": [
      {
        "route": "/deployment-status.json",
        "status": 200,
        "ok": true
      },
      {
        "route": "/domain-continuity.json",
        "status": 200,
        "ok": true
      },
      {
        "route": "/runtime-fingerprint.txt",
        "status": 200,
        "ok": true
      },
      {
        "route": "/live-shell-verification.html",
        "status": 200,
        "ok": true
      },
      {
        "route": "/host-binding-audit.html",
        "status": 200,
        "ok": true
      },
      {
        "route": "/api-continuity-audit.html",
        "status": 200,
        "ok": true
      },
      {
        "route": "/warranty",
        "status": 200,
        "ok": true
      },
      {
        "route": "/referrals",
        "status": 200,
        "ok": true
      },
      {
        "route": "/commit-witness-c21c4544ced7658f74ca9c026c6c7f2b324679b4.txt",
        "status": 200,
        "ok": true
      }
    ],
    "failures": []
  }
]
