[
  {
    "attempt": 6,
    "targetSwaName": "fca-frontend",
    "targetDefaultHost": "delightful-mushroom-0de67860f.7.azurestaticapps.net",
    "targetGitSha": "0f4fb14c2c4384ad4a81da32e53dfed76dc70bbc",
    "host": "futurecontractorsofamerica.com",
    "deploymentGitSha": "0d897f5b65eb0e24b9d796ff85eb46b76db70758",
    "runtimeGitSha": "0d897f5b65eb0e24b9d796ff85eb46b76db70758",
    "commitWitnessRoute": "/commit-witness-0d897f5b65eb0e24b9d796ff85eb46b76db70758.txt",
    "expectedHosts": [
      "futurecontractorsofamerica.com",
      "www.futurecontractorsofamerica.com",
      "delightful-mushroom-0de67860f.7.azurestaticapps.net"
    ],
    "routeChecks": [
      {
        "route": "/deployment-status.json",
        "status": 200,
        "ok": true
      },
      {
        "route": "/domain-continuity.json",
        "status": 200,
        "ok": true
      },
      {
        "route": "/runtime-fingerprint.txt",
        "status": 200,
        "ok": true
      },
      {
        "route": "/live-shell-verification.html",
        "status": 200,
        "ok": true
      },
      {
        "route": "/host-binding-audit.html",
        "status": 200,
        "ok": true
      },
      {
        "route": "/api-continuity-audit.html",
        "status": 200,
        "ok": true
      },
      {
        "route": "/warranty",
        "status": 200,
        "ok": true
      },
      {
        "route": "/referrals",
        "status": 200,
        "ok": true
      },
      {
        "route": "/leads/index.html",
        "status": 200,
        "ok": true
      },
      {
        "route": "/leads/new.html",
        "status": 200,
        "ok": true
      },
      {
        "route": "/config/auricrux-central.js",
        "status": 404,
        "ok": false
      },
      {
        "route": "/bids/detail.html",
        "status": 200,
        "ok": true
      },
      {
        "route": "/commit-witness-0f4fb14c2c4384ad4a81da32e53dfed76dc70bbc.txt",
        "status": 404,
        "ok": false
      }
    ],
    "failures": [
      "https://futurecontractorsofamerica.com/commit-witness-0f4fb14c2c4384ad4a81da32e53dfed76dc70bbc.txt returned 404",
      "futurecontractorsofamerica.com is serving stale deployment-status SHA 0d897f5b65eb0e24b9d796ff85eb46b76db70758; expected 0f4fb14c2c4384ad4a81da32e53dfed76dc70bbc",
      "futurecontractorsofamerica.com is serving stale runtime-fingerprint SHA 0d897f5b65eb0e24b9d796ff85eb46b76db70758; expected 0f4fb14c2c4384ad4a81da32e53dfed76dc70bbc",
      "futurecontractorsofamerica.com deployment manifest reports commit witness /commit-witness-0d897f5b65eb0e24b9d796ff85eb46b76db70758.txt; expected /commit-witness-0f4fb14c2c4384ad4a81da32e53dfed76dc70bbc.txt",
      "https://futurecontractorsofamerica.com/config/auricrux-central.js returned 404",
      "https://futurecontractorsofamerica.com/commit-witness-0f4fb14c2c4384ad4a81da32e53dfed76dc70bbc.txt returned 404"
    ]
  },
  {
    "attempt": 6,
    "targetSwaName": "fca-frontend",
    "targetDefaultHost": "delightful-mushroom-0de67860f.7.azurestaticapps.net",
    "targetGitSha": "0f4fb14c2c4384ad4a81da32e53dfed76dc70bbc",
    "host": "www.futurecontractorsofamerica.com",
    "deploymentGitSha": "0d897f5b65eb0e24b9d796ff85eb46b76db70758",
    "runtimeGitSha": "0d897f5b65eb0e24b9d796ff85eb46b76db70758",
    "commitWitnessRoute": "/commit-witness-0d897f5b65eb0e24b9d796ff85eb46b76db70758.txt",
    "expectedHosts": [
      "futurecontractorsofamerica.com",
      "www.futurecontractorsofamerica.com",
      "delightful-mushroom-0de67860f.7.azurestaticapps.net"
    ],
    "routeChecks": [
      {
        "route": "/deployment-status.json",
        "status": 200,
        "ok": true
      },
      {
        "route": "/domain-continuity.json",
        "status": 200,
        "ok": true
      },
      {
        "route": "/runtime-fingerprint.txt",
        "status": 200,
        "ok": true
      },
      {
        "route": "/live-shell-verification.html",
        "status": 200,
        "ok": true
      },
      {
        "route": "/host-binding-audit.html",
        "status": 200,
        "ok": true
      },
      {
        "route": "/api-continuity-audit.html",
        "status": 200,
        "ok": true
      },
      {
        "route": "/warranty",
        "status": 200,
        "ok": true
      },
      {
        "route": "/referrals",
        "status": 200,
        "ok": true
      },
      {
        "route": "/leads/index.html",
        "status": 200,
        "ok": true
      },
      {
        "route": "/leads/new.html",
        "status": 200,
        "ok": true
      },
      {
        "route": "/config/auricrux-central.js",
        "status": 404,
        "ok": false
      },
      {
        "route": "/bids/detail.html",
        "status": 200,
        "ok": true
      },
      {
        "route": "/commit-witness-0f4fb14c2c4384ad4a81da32e53dfed76dc70bbc.txt",
        "status": 404,
        "ok": false
      }
    ],
    "failures": [
      "https://www.futurecontractorsofamerica.com/commit-witness-0f4fb14c2c4384ad4a81da32e53dfed76dc70bbc.txt returned 404",
      "www.futurecontractorsofamerica.com is serving stale deployment-status SHA 0d897f5b65eb0e24b9d796ff85eb46b76db70758; expected 0f4fb14c2c4384ad4a81da32e53dfed76dc70bbc",
      "www.futurecontractorsofamerica.com is serving stale runtime-fingerprint SHA 0d897f5b65eb0e24b9d796ff85eb46b76db70758; expected 0f4fb14c2c4384ad4a81da32e53dfed76dc70bbc",
      "www.futurecontractorsofamerica.com deployment manifest reports commit witness /commit-witness-0d897f5b65eb0e24b9d796ff85eb46b76db70758.txt; expected /commit-witness-0f4fb14c2c4384ad4a81da32e53dfed76dc70bbc.txt",
      "https://www.futurecontractorsofamerica.com/config/auricrux-central.js returned 404",
      "https://www.futurecontractorsofamerica.com/commit-witness-0f4fb14c2c4384ad4a81da32e53dfed76dc70bbc.txt returned 404"
    ]
  },
  {
    "attempt": 6,
    "targetSwaName": "fca-frontend",
    "targetDefaultHost": "delightful-mushroom-0de67860f.7.azurestaticapps.net",
    "targetGitSha": "0f4fb14c2c4384ad4a81da32e53dfed76dc70bbc",
    "host": "delightful-mushroom-0de67860f.7.azurestaticapps.net",
    "deploymentGitSha": "0d897f5b65eb0e24b9d796ff85eb46b76db70758",
    "runtimeGitSha": "0d897f5b65eb0e24b9d796ff85eb46b76db70758",
    "commitWitnessRoute": "/commit-witness-0d897f5b65eb0e24b9d796ff85eb46b76db70758.txt",
    "expectedHosts": [
      "futurecontractorsofamerica.com",
      "www.futurecontractorsofamerica.com",
      "delightful-mushroom-0de67860f.7.azurestaticapps.net"
    ],
    "routeChecks": [
      {
        "route": "/deployment-status.json",
        "status": 200,
        "ok": true
      },
      {
        "route": "/domain-continuity.json",
        "status": 200,
        "ok": true
      },
      {
        "route": "/runtime-fingerprint.txt",
        "status": 200,
        "ok": true
      },
      {
        "route": "/live-shell-verification.html",
        "status": 200,
        "ok": true
      },
      {
        "route": "/host-binding-audit.html",
        "status": 200,
        "ok": true
      },
      {
        "route": "/api-continuity-audit.html",
        "status": 200,
        "ok": true
      },
      {
        "route": "/warranty",
        "status": 200,
        "ok": true
      },
      {
        "route": "/referrals",
        "status": 200,
        "ok": true
      },
      {
        "route": "/leads/index.html",
        "status": 200,
        "ok": true
      },
      {
        "route": "/leads/new.html",
        "status": 200,
        "ok": true
      },
      {
        "route": "/config/auricrux-central.js",
        "status": 404,
        "ok": false
      },
      {
        "route": "/bids/detail.html",
        "status": 200,
        "ok": true
      },
      {
        "route": "/commit-witness-0f4fb14c2c4384ad4a81da32e53dfed76dc70bbc.txt",
        "status": 404,
        "ok": false
      }
    ],
    "failures": [
      "https://delightful-mushroom-0de67860f.7.azurestaticapps.net/commit-witness-0f4fb14c2c4384ad4a81da32e53dfed76dc70bbc.txt returned 404",
      "delightful-mushroom-0de67860f.7.azurestaticapps.net is serving stale deployment-status SHA 0d897f5b65eb0e24b9d796ff85eb46b76db70758; expected 0f4fb14c2c4384ad4a81da32e53dfed76dc70bbc",
      "delightful-mushroom-0de67860f.7.azurestaticapps.net is serving stale runtime-fingerprint SHA 0d897f5b65eb0e24b9d796ff85eb46b76db70758; expected 0f4fb14c2c4384ad4a81da32e53dfed76dc70bbc",
      "delightful-mushroom-0de67860f.7.azurestaticapps.net deployment manifest reports commit witness /commit-witness-0d897f5b65eb0e24b9d796ff85eb46b76db70758.txt; expected /commit-witness-0f4fb14c2c4384ad4a81da32e53dfed76dc70bbc.txt",
      "https://delightful-mushroom-0de67860f.7.azurestaticapps.net/config/auricrux-central.js returned 404",
      "https://delightful-mushroom-0de67860f.7.azurestaticapps.net/commit-witness-0f4fb14c2c4384ad4a81da32e53dfed76dc70bbc.txt returned 404"
    ]
  }
]
