{
  "service": "fca-bid-tracker",
  "witnessType": "domain-continuity",
  "generatedAt": "2026-07-02T17:30:46.426Z",
  "source": "github-actions",
  "gitRef": "refs/heads/main",
  "gitSha": "8f03020229e3f04156e16fc0d41ad52101fe803c",
  "runId": "28609099378",
  "defaultHost": "delightful-mushroom-0de67860f.7.azurestaticapps.net",
  "expectedHosts": [
    "futurecontractorsofamerica.com",
    "www.futurecontractorsofamerica.com",
    "delightful-mushroom-0de67860f.7.azurestaticapps.net"
  ],
  "canonicalRoutes": [
    "/",
    "/platform",
    "/login",
    "/pricing",
    "/contact",
    "/auricrux",
    "/academy",
    "/portal/platform",
    "/portal/projects",
    "/portal/files",
    "/portal/messages",
    "/portal/notifications",
    "/portal/bids",
    "/portal/billing",
    "/portal/support",
    "/portal/admin",
    "/portal/profile",
    "/portal/auricrux",
    "/live-shell-verification.html",
    "/deployment-status.json"
  ],
  "knownUnexpectedRoutes": [
    "/team"
  ],
  "continuityIntent": "apex-and-www-must-resolve-to-same-governed-swa-artifact"
}
