{
  "packet": "062Y",
  "generatedAt": "2026-07-04T13:07:27.357Z",
  "currentRunId": "28707159975",
  "currentSha": "719df3a550cadcd897589074fb8c3c52c5c813e4",
  "targetReached": true,
  "records": [
    {
      "file": "build-evidence-report.json",
      "exists": true,
      "provenance": "github_actions_ci",
      "ciPersisted": true,
      "ciRunId": "28707159975",
      "ciCommitSha": "719df3a550cadcd897589074fb8c3c52c5c813e4"
    },
    {
      "file": "build-proof-lane-validation.json",
      "exists": true,
      "provenance": "github_actions_ci",
      "ciPersisted": true,
      "ciRunId": "28707159975",
      "ciCommitSha": "719df3a550cadcd897589074fb8c3c52c5c813e4"
    },
    {
      "file": "build-proof-lane-report.json",
      "exists": true,
      "provenance": "github_actions_ci",
      "ciPersisted": true,
      "ciRunId": "28707159975",
      "ciCommitSha": "719df3a550cadcd897589074fb8c3c52c5c813e4"
    },
    {
      "file": "packet-letter-lock-validation.json",
      "exists": true,
      "provenance": "github_actions_ci",
      "ciPersisted": true,
      "ciRunId": "28707159975",
      "ciCommitSha": "719df3a550cadcd897589074fb8c3c52c5c813e4"
    },
    {
      "file": "packet-letter-lock-report.json",
      "exists": true,
      "provenance": "github_actions_ci",
      "ciPersisted": true,
      "ciRunId": "28707159975",
      "ciCommitSha": "719df3a550cadcd897589074fb8c3c52c5c813e4"
    }
  ]
}