{
  "packet": "062Y",
  "generatedAt": "2026-06-24T12:42:26.287Z",
  "provenance": "github_actions_ci",
  "ciPersisted": true,
  "ciRunId": "28099242990",
  "ciCommitSha": "171a717906118310328f0968d40d4bc7e54bb8b1",
  "stamped": [
    "build-evidence-report.json",
    "build-proof-lane-validation.json",
    "build-proof-lane-report.json",
    "packet-letter-lock-validation.json",
    "packet-letter-lock-report.json",
    "build-evidence-report.md",
    "build-proof-lane-validation.md",
    "build-proof-lane-report.md",
    "packet-letter-lock-validation.md",
    "packet-letter-lock-report.md"
  ],
  "missing": [],
  "success": true
}