{
  "packet": "062Y",
  "generatedAt": "2026-06-21T18:36:51.513Z",
  "currentRunId": "27913739715",
  "currentSha": "f01866192506a76f266fab6690637fd484733566",
  "targetReached": true,
  "records": [
    {
      "file": "build-evidence-report.json",
      "exists": true,
      "provenance": "github_actions_ci",
      "ciPersisted": true,
      "ciRunId": "27913739715",
      "ciCommitSha": "f01866192506a76f266fab6690637fd484733566"
    },
    {
      "file": "build-proof-lane-validation.json",
      "exists": true,
      "provenance": "github_actions_ci",
      "ciPersisted": true,
      "ciRunId": "27913739715",
      "ciCommitSha": "f01866192506a76f266fab6690637fd484733566"
    },
    {
      "file": "build-proof-lane-report.json",
      "exists": true,
      "provenance": "github_actions_ci",
      "ciPersisted": true,
      "ciRunId": "27913739715",
      "ciCommitSha": "f01866192506a76f266fab6690637fd484733566"
    },
    {
      "file": "packet-letter-lock-validation.json",
      "exists": true,
      "provenance": "github_actions_ci",
      "ciPersisted": true,
      "ciRunId": "27913739715",
      "ciCommitSha": "f01866192506a76f266fab6690637fd484733566"
    },
    {
      "file": "packet-letter-lock-report.json",
      "exists": true,
      "provenance": "github_actions_ci",
      "ciPersisted": true,
      "ciRunId": "27913739715",
      "ciCommitSha": "f01866192506a76f266fab6690637fd484733566"
    }
  ]
}