{
  "packet": "062Y",
  "generatedAt": "2026-06-22T14:51:41.722Z",
  "success": false,
  "observedCommitSha": "c2baf7fb62338ae9b4c133a394ac0c772ed3b601",
  "observedCommitMessage": "Persist live deployment run witness for run 27957872182",
  "observedWitness": {
    "provenance": "github_actions_ci",
    "ciPersisted": true,
    "ciRunId": "27961527674",
    "ciCommitSha": "2564121a0c381ad3e1be2e4f3cf85f1bddee1ad1",
    "workflow": "FCA Live Deployment Proof Stamp"
  },
  "failures": [
    "live deployment run witness does not point at the expected source commit for the observed witness run"
  ]
}