{
  "packet": "062Y",
  "generatedAt": "2026-06-20T00:48:41.935Z",
  "success": false,
  "observedCommitSha": "74017b70a5d51fff5efbc47672174efbf4135597",
  "observedCommitMessage": "Persist live deployment run witness for run 27855062102",
  "observedWitness": {
    "provenance": "github_actions_ci",
    "ciPersisted": true,
    "ciRunId": "27855101931",
    "ciCommitSha": "f03236986bbe436682ce44720a373263d776a7ac",
    "workflow": "FCA Live Deployment Proof Stamp"
  },
  "failures": [
    "live deployment run witness does not point at the expected source commit for the observed witness run"
  ]
}