{
  "packet": "062Y",
  "generatedAt": "2026-06-28T03:35:45.111Z",
  "github": {
    "repository": "Future-Contractors-of-America-LLC/fca-bid-tracker",
    "ref": "refs/heads/main",
    "sha": "f1bb5ffa225cdf151b7bbbec084b85e4625fcbe8",
    "runId": "28310206581",
    "workflow": "FCA Runtime Smoke Validation"
  },
  "artifacts": {
    "buildEvidencePresent": true,
    "runtimeSmokePresent": true
  },
  "buildEvidenceSummary": {
    "packet": "062Y",
    "buildSystem": "npm run build",
    "build": "npx vite build && node scripts/post-spa-build.mjs",
    "hasBuildValidationWorkflow": true,
    "invokesBuildSystem": true
  },
  "runtimeSmokeSummary": {
    "packet": "062Y",
    "total": 10,
    "passed": 8,
    "failed": 2
  },
  "gateAssessment": {
    "buildEvidenceReady": true,
    "runtimeSmokeReady": true,
    "runtimeSmokePass": false
  }
}