{
  "packet": "062Y",
  "generatedAt": "2026-06-17T20:22:48.890Z",
  "github": {
    "repository": "Future-Contractors-of-America-LLC/fca-bid-tracker",
    "ref": "refs/heads/main",
    "sha": "1a0c4f1e8903ae1b91598e5b59d8d7d2ad5575e9",
    "runId": "27717351758",
    "workflow": "FCA Runtime Smoke Validation"
  },
  "artifacts": {
    "buildEvidencePresent": true,
    "runtimeSmokePresent": true
  },
  "buildEvidenceSummary": {
    "packet": "062Y",
    "buildSystem": "npm run build",
    "build": "bash ./build.sh",
    "hasBuildValidationWorkflow": true,
    "invokesBuildSystem": true
  },
  "runtimeSmokeSummary": {
    "packet": "062Y",
    "total": 10,
    "passed": 10,
    "failed": 0
  },
  "gateAssessment": {
    "buildEvidenceReady": true,
    "runtimeSmokeReady": true,
    "runtimeSmokePass": true
  }
}