{
  "packet": "062Y",
  "generatedAt": "2026-06-20T21:54:25.463Z",
  "github": {
    "repository": "Future-Contractors-of-America-LLC/fca-bid-tracker",
    "ref": "refs/heads/main",
    "sha": "75a708ccb3fbcc54c1f478b8add3ade07dccfbb7",
    "runId": "27885013738",
    "workflow": "FCA Runtime Smoke Validation"
  },
  "artifacts": {
    "buildEvidencePresent": true,
    "runtimeSmokePresent": true
  },
  "buildEvidenceSummary": {
    "packet": "062Y",
    "buildSystem": "npm run build",
    "build": "npx vite build && node scripts/post-spa-build.mjs",
    "hasBuildValidationWorkflow": true,
    "invokesBuildSystem": true
  },
  "runtimeSmokeSummary": {
    "packet": "062Y",
    "total": 10,
    "passed": 9,
    "failed": 1
  },
  "gateAssessment": {
    "buildEvidenceReady": true,
    "runtimeSmokeReady": true,
    "runtimeSmokePass": false
  }
}